{
  "nodes": {
    "SitePage /dev-404-page/": {
      "jsonName": "dev-404-page-5f9",
      "internalComponentName": "ComponentDev404Page",
      "path": "/dev-404-page/",
      "component": "C:/Repos/UltimateLaundrySolutions/.cache/dev-404-page.js",
      "componentChunkName": "component---cache-dev-404-page-js",
      "context": {},
      "pluginCreator___NODE": "Plugin dev-404-page",
      "pluginCreatorId": "Plugin dev-404-page",
      "componentPath": "C:/Repos/UltimateLaundrySolutions/.cache/dev-404-page.js",
      "id": "SitePage /dev-404-page/",
      "parent": "SOURCE",
      "children": [],
      "internal": {
        "type": "SitePage",
        "contentDigest": "2f27213d1f893cdb1267d8f7b8e9756f",
        "description": "Plugin dev-404-page",
        "owner": "internal-data-bridge"
      }
    },
    "Plugin dev-404-page": {
      "resolve": "C:/Repos/UltimateLaundrySolutions/node_modules/gatsby/dist/internal-plugins/dev-404-page",
      "id": "Plugin dev-404-page",
      "name": "dev-404-page",
      "version": "1.0.0",
      "pluginOptions": {
        "plugins": []
      },
      "nodeAPIs": [
        "createPagesStatefully"
      ],
      "browserAPIs": [],
      "ssrAPIs": [],
      "pluginFilepath": "C:/Repos/UltimateLaundrySolutions/node_modules/gatsby/dist/internal-plugins/dev-404-page",
      "packageJson": {
        "name": "dev-404-page",
        "description": "Internal plugin to add a 404 page in development with helpful information",
        "version": "1.0.0",
        "main": "index.js",
        "author": "Kyle Mathews <mathews.kyle@gmail.com>",
        "license": "MIT",
        "dependencies": [],
        "devDependencies": [],
        "peerDependencies": [],
        "optionalDependecies": [],
        "bundledDependecies": []
      },
      "parent": "SOURCE",
      "children": [],
      "internal": {
        "contentDigest": "a48acba68de28b41b14f11587ef52739",
        "type": "SitePlugin",
        "owner": "internal-data-bridge"
      }
    },
    "Plugin load-babel-config": {
      "resolve": "C:/Repos/UltimateLaundrySolutions/node_modules/gatsby/dist/internal-plugins/load-babel-config",
      "id": "Plugin load-babel-config",
      "name": "load-babel-config",
      "version": "1.0.0",
      "pluginOptions": {
        "plugins": []
      },
      "nodeAPIs": [
        "onPreBootstrap"
      ],
      "browserAPIs": [],
      "ssrAPIs": [],
      "pluginFilepath": "C:/Repos/UltimateLaundrySolutions/node_modules/gatsby/dist/internal-plugins/load-babel-config",
      "packageJson": {
        "name": "load-babel-config",
        "description": "Internal plugin that handles loading Babel configs",
        "version": "1.0.0",
        "main": "index.js",
        "author": "Kyle Mathews <mathews.kyle@gmail.com>",
        "license": "MIT",
        "dependencies": [],
        "devDependencies": [],
        "peerDependencies": [],
        "optionalDependecies": [],
        "bundledDependecies": []
      },
      "parent": "SOURCE",
      "children": [],
      "internal": {
        "contentDigest": "dd7b962d64d0ecd4c3f496efd2f45f65",
        "type": "SitePlugin",
        "owner": "internal-data-bridge"
      }
    },
    "Plugin internal-data-bridge": {
      "resolve": "C:/Repos/UltimateLaundrySolutions/node_modules/gatsby/dist/internal-plugins/internal-data-bridge",
      "id": "Plugin internal-data-bridge",
      "name": "internal-data-bridge",
      "version": "1.0.0",
      "pluginOptions": {
        "plugins": []
      },
      "nodeAPIs": [
        "sourceNodes",
        "onCreatePage"
      ],
      "browserAPIs": [],
      "ssrAPIs": [],
      "pluginFilepath": "C:/Repos/UltimateLaundrySolutions/node_modules/gatsby/dist/internal-plugins/internal-data-bridge",
      "packageJson": {
        "name": "internal-data-bridge",
        "description": "An internal Gatsby plugin which creates data nodes from internal data",
        "version": "1.0.0",
        "main": "index.js",
        "author": "Kyle Mathews <mathews.kyle@gmail.com>",
        "license": "MIT",
        "dependencies": [],
        "devDependencies": [],
        "peerDependencies": [],
        "optionalDependecies": [],
        "bundledDependecies": []
      },
      "parent": "SOURCE",
      "children": [],
      "internal": {
        "contentDigest": "eb92d5c5fea0583da0a6c32b71342162",
        "type": "SitePlugin",
        "owner": "internal-data-bridge"
      }
    },
    "Plugin prod-404": {
      "resolve": "C:/Repos/UltimateLaundrySolutions/node_modules/gatsby/dist/internal-plugins/prod-404",
      "id": "Plugin prod-404",
      "name": "prod-404",
      "version": "1.0.0",
      "pluginOptions": {
        "plugins": []
      },
      "nodeAPIs": [
        "onCreatePage"
      ],
      "browserAPIs": [],
      "ssrAPIs": [],
      "pluginFilepath": "C:/Repos/UltimateLaundrySolutions/node_modules/gatsby/dist/internal-plugins/prod-404",
      "packageJson": {
        "name": "prod-404",
        "description": "Internal plugin to detect various flavors of 404 pages and ensure there's a 404.html path created as well to ensure compatability with static hosts",
        "version": "1.0.0",
        "main": "index.js",
        "author": "Kyle Mathews <mathews.kyle@gmail.com>",
        "license": "MIT",
        "dependencies": [],
        "devDependencies": [],
        "peerDependencies": [],
        "optionalDependecies": [],
        "bundledDependecies": []
      },
      "parent": "SOURCE",
      "children": [],
      "internal": {
        "contentDigest": "7e62e8277fe9d084cc09b19a120a3d10",
        "type": "SitePlugin",
        "owner": "internal-data-bridge"
      }
    },
    "Plugin query-runner": {
      "resolve": "C:/Repos/UltimateLaundrySolutions/node_modules/gatsby/dist/internal-plugins/query-runner",
      "id": "Plugin query-runner",
      "name": "query-runner",
      "version": "1.0.0",
      "pluginOptions": {
        "plugins": []
      },
      "nodeAPIs": [
        "onCreatePage"
      ],
      "browserAPIs": [],
      "ssrAPIs": [],
      "pluginFilepath": "C:/Repos/UltimateLaundrySolutions/node_modules/gatsby/dist/internal-plugins/query-runner",
      "packageJson": {
        "name": "query-runner",
        "description": "Internal plugin for running queries",
        "version": "1.0.0",
        "main": "index.js",
        "author": "",
        "license": "MIT",
        "dependencies": [],
        "devDependencies": [],
        "peerDependencies": [],
        "optionalDependecies": [],
        "bundledDependecies": []
      },
      "parent": "SOURCE",
      "children": [],
      "internal": {
        "contentDigest": "28c7e29251fae4d36fe62844313ed720",
        "type": "SitePlugin",
        "owner": "internal-data-bridge"
      }
    },
    "Plugin gatsby-plugin-typescript": {
      "resolve": "C:/Repos/UltimateLaundrySolutions/node_modules/gatsby-plugin-typescript",
      "id": "Plugin gatsby-plugin-typescript",
      "name": "gatsby-plugin-typescript",
      "version": "2.0.0",
      "pluginOptions": {
        "plugins": []
      },
      "nodeAPIs": [
        "resolvableExtensions",
        "onCreateBabelConfig",
        "onCreateWebpackConfig"
      ],
      "browserAPIs": [],
      "ssrAPIs": [],
      "pluginFilepath": "C:/Repos/UltimateLaundrySolutions/node_modules/gatsby-plugin-typescript",
      "packageJson": {
        "name": "gatsby-plugin-typescript",
        "description": "Adds TypeScript support to Gatsby",
        "version": "2.0.0",
        "main": "index.js",
        "keywords": [
          "gatsby",
          "gatsby-plugin",
          "typescript"
        ],
        "author": "Kyle Mathews <mathews.kyle@gmail.com>",
        "license": "MIT",
        "dependencies": [
          {
            "name": "@babel/preset-typescript",
            "version": "^7.0.0"
          },
          {
            "name": "@babel/runtime",
            "version": "^7.0.0"
          },
          {
            "name": "babel-plugin-remove-graphql-queries",
            "version": "^2.0.2-rc.3"
          }
        ],
        "devDependencies": [
          {
            "name": "@babel/cli",
            "version": "^7.0.0"
          },
          {
            "name": "@babel/core",
            "version": "^7.0.0"
          },
          {
            "name": "cross-env",
            "version": "^5.1.4"
          }
        ],
        "peerDependencies": [
          {
            "name": "gatsby",
            "version": ">2.0.0-alpha"
          }
        ],
        "optionalDependecies": [],
        "bundledDependecies": []
      },
      "parent": "SOURCE",
      "children": [],
      "internal": {
        "contentDigest": "7c24eb6d1dc870559517ff12e6b003a5",
        "type": "SitePlugin",
        "owner": "internal-data-bridge"
      }
    },
    "Plugin default-site-plugin": {
      "resolve": "C:/Repos/UltimateLaundrySolutions",
      "id": "Plugin default-site-plugin",
      "name": "default-site-plugin",
      "version": "a6c17ee989b5b3ff8e3499bffa22f82a",
      "pluginOptions": {
        "plugins": []
      },
      "nodeAPIs": [],
      "browserAPIs": [],
      "ssrAPIs": [],
      "pluginFilepath": "C:/Repos/UltimateLaundrySolutions",
      "packageJson": {
        "name": "ultimatelaundrysolutions",
        "version": "0.0.0",
        "license": "UNLICENSED",
        "dependencies": [
          {
            "name": "@types/reactstrap",
            "version": "^6.4.2"
          },
          {
            "name": "@types/styled-components",
            "version": "^4.0.2"
          },
          {
            "name": "bootstrap",
            "version": "^4.1.3"
          },
          {
            "name": "gatsby",
            "version": "^2.0.29"
          },
          {
            "name": "gatsby-plugin-typescript",
            "version": "^2.0.0"
          },
          {
            "name": "jquery",
            "version": "^3.3.1"
          },
          {
            "name": "popper.js",
            "version": "^1.14.4"
          },
          {
            "name": "react",
            "version": "^16.5.2"
          },
          {
            "name": "react-dom",
            "version": "^16.5.2"
          },
          {
            "name": "reactstrap",
            "version": "^6.5.0"
          }
        ],
        "devDependencies": [
          {
            "name": "gatsby-cli",
            "version": "^2.4.3"
          },
          {
            "name": "styled-components",
            "version": "^4.0.2"
          },
          {
            "name": "typescript",
            "version": "^3.1.3"
          }
        ],
        "peerDependencies": [],
        "optionalDependecies": [],
        "bundledDependecies": []
      },
      "parent": "SOURCE",
      "children": [],
      "internal": {
        "contentDigest": "cc0b827c38e7aff29773de970b6810a9",
        "type": "SitePlugin",
        "owner": "internal-data-bridge"
      }
    },
    "Plugin gatsby-plugin-page-creator": {
      "resolve": "C:/Repos/UltimateLaundrySolutions/node_modules/gatsby-plugin-page-creator",
      "id": "Plugin gatsby-plugin-page-creator",
      "name": "gatsby-plugin-page-creator",
      "version": "2.0.1",
      "pluginOptions": {
        "plugins": [],
        "path": "C:/Repos/UltimateLaundrySolutions/src/pages",
        "pathCheck": false
      },
      "nodeAPIs": [
        "createPagesStatefully"
      ],
      "browserAPIs": [],
      "ssrAPIs": [],
      "pluginFilepath": "C:/Repos/UltimateLaundrySolutions/node_modules/gatsby-plugin-page-creator",
      "packageJson": {
        "name": "gatsby-plugin-page-creator",
        "description": "Gatsby plugin that automatically creates pages from React components in specified directories",
        "version": "2.0.1",
        "main": "index.js",
        "keywords": [
          "gatsby",
          "gatsby-plugin"
        ],
        "author": "Kyle Mathews <mathews.kyle@gmail.com>",
        "license": "MIT",
        "dependencies": [
          {
            "name": "@babel/runtime",
            "version": "^7.0.0"
          },
          {
            "name": "bluebird",
            "version": "^3.5.0"
          },
          {
            "name": "chokidar",
            "version": "^1.7.0"
          },
          {
            "name": "fs-exists-cached",
            "version": "^1.0.0"
          },
          {
            "name": "glob",
            "version": "^7.1.1"
          },
          {
            "name": "lodash",
            "version": "^4.17.10"
          },
          {
            "name": "parse-filepath",
            "version": "^1.0.1"
          },
          {
            "name": "slash",
            "version": "^1.0.0"
          }
        ],
        "devDependencies": [
          {
            "name": "@babel/cli",
            "version": "^7.0.0"
          },
          {
            "name": "@babel/core",
            "version": "^7.0.0"
          },
          {
            "name": "cross-env",
            "version": "^5.0.5"
          }
        ],
        "peerDependencies": [
          {
            "name": "gatsby",
            "version": ">2.0.0-alpha"
          }
        ],
        "optionalDependecies": [],
        "bundledDependecies": []
      },
      "parent": "SOURCE",
      "children": [],
      "internal": {
        "contentDigest": "ea2654b6cd03a99af40ae5db5d3a2b8f",
        "type": "SitePlugin",
        "owner": "internal-data-bridge"
      }
    },
    "Site": {
      "siteMetadata": {},
      "port": "8000",
      "host": "localhost",
      "pathPrefix": "",
      "polyfill": true,
      "buildTime": "2018-11-08T01:02:36.636Z",
      "id": "Site",
      "parent": "SOURCE",
      "children": [],
      "internal": {
        "contentDigest": "433cba6776e91604abfbd6cab625ce86",
        "type": "Site",
        "owner": "internal-data-bridge"
      }
    },
    "SitePage /": {
      "jsonName": "index",
      "internalComponentName": "ComponentIndex",
      "path": "/",
      "component": "C:/Repos/UltimateLaundrySolutions/src/pages/index.tsx",
      "componentChunkName": "component---src-pages-index-tsx",
      "context": {},
      "pluginCreator___NODE": "Plugin gatsby-plugin-page-creator",
      "pluginCreatorId": "Plugin gatsby-plugin-page-creator",
      "componentPath": "C:/Repos/UltimateLaundrySolutions/src/pages/index.tsx",
      "id": "SitePage /",
      "parent": "SOURCE",
      "children": [],
      "internal": {
        "type": "SitePage",
        "contentDigest": "a8f63541e6c31ac0be95c972dad83ad7",
        "description": "Plugin gatsby-plugin-page-creator",
        "owner": "internal-data-bridge"
      }
    },
    "SitePage /signup/": {
      "jsonName": "signup-371",
      "internalComponentName": "ComponentSignup",
      "path": "/signup/",
      "component": "C:/Repos/UltimateLaundrySolutions/src/pages/signup.tsx",
      "componentChunkName": "component---src-pages-signup-tsx",
      "context": {},
      "pluginCreator___NODE": "Plugin gatsby-plugin-page-creator",
      "pluginCreatorId": "Plugin gatsby-plugin-page-creator",
      "componentPath": "C:/Repos/UltimateLaundrySolutions/src/pages/signup.tsx",
      "id": "SitePage /signup/",
      "parent": "SOURCE",
      "children": [],
      "internal": {
        "type": "SitePage",
        "contentDigest": "a402c10e7b95a700572091d149e9ed12",
        "description": "Plugin gatsby-plugin-page-creator",
        "owner": "internal-data-bridge"
      }
    }
  },
  "status": {
    "plugins": {},
    "PLUGINS_HASH": "f88923b146cec8c8c0c4b89bef876094"
  },
  "componentDataDependencies": {
    "nodes": {},
    "connections": {}
  },
  "jsonDataPaths": {
    "dev-404-page-5f9": "920/path---dev-404-page-5-f-9-fab-NZuapzHg3X9TaN1iIixfv1W23E",
    "index": "173/path---index-6a9-NZuapzHg3X9TaN1iIixfv1W23E",
    "signup-371": "571/path---signup-371-33e-NZuapzHg3X9TaN1iIixfv1W23E"
  },
  "components": {
    "C:/Repos/UltimateLaundrySolutions/.cache/dev-404-page.js": {
      "query": "",
      "componentPath": "C:/Repos/UltimateLaundrySolutions/.cache/dev-404-page.js"
    },
    "C:/Repos/UltimateLaundrySolutions/src/pages/index.tsx": {
      "query": "",
      "componentPath": "C:/Repos/UltimateLaundrySolutions/src/pages/index.tsx"
    },
    "C:/Repos/UltimateLaundrySolutions/src/pages/signup.tsx": {
      "query": "",
      "componentPath": "C:/Repos/UltimateLaundrySolutions/src/pages/signup.tsx"
    }
  },
  "staticQueryComponents": {}
}